<?xml version='1.0' encoding='UTF-8'?>
<TRIAL CARDINALITY="1" DIALOGUE="no" DOMAIN="furniture" ID="28m23l1t57" MODALITY="spoken">
  <DOMAIN>
    <ENTITY ID="11" IMAGE="chairLeftGreyLarge.gif" TYPE="target">
      <ATTRIBUTE NAME="size" TYPE="literal" VALUE="large"/>
      <ATTRIBUTE NAME="type" TYPE="literal" VALUE="chair"/>
      <ATTRIBUTE NAME="orientation" TYPE="literal" VALUE="left"/>
      <ATTRIBUTE NAME="colour" TYPE="literal" VALUE="grey"/>
    </ENTITY>
    <ENTITY ID="12" IMAGE="chairLeftRedLarge.gif" TYPE="distractor">
      <ATTRIBUTE NAME="size" TYPE="literal" VALUE="large"/>
      <ATTRIBUTE NAME="type" TYPE="literal" VALUE="chair"/>
      <ATTRIBUTE NAME="orientation" TYPE="literal" VALUE="left"/>
      <ATTRIBUTE NAME="colour" TYPE="literal" VALUE="red"/>
    </ENTITY>
    <ENTITY ID="9" IMAGE="chairLeftBlueLarge.gif" TYPE="distractor">
      <ATTRIBUTE NAME="size" TYPE="literal" VALUE="large"/>
      <ATTRIBUTE NAME="type" TYPE="literal" VALUE="chair"/>
      <ATTRIBUTE NAME="orientation" TYPE="literal" VALUE="left"/>
      <ATTRIBUTE NAME="colour" TYPE="literal" VALUE="blue"/>
    </ENTITY>
    <ENTITY IMAGE="chairLeftGreySmall.gif" TYPE="distractor">
      <ATTRIBUTE NAME="size" TYPE="literal" VALUE="small"/>
      <ATTRIBUTE NAME="type" TYPE="literal" VALUE="chair"/>
      <ATTRIBUTE NAME="orientation" TYPE="literal" VALUE="left"/>
      <ATTRIBUTE NAME="colour" TYPE="literal" VALUE="grey"/>
    </ENTITY>
    <ENTITY IMAGE="fanRightRedSmall.gif" TYPE="distractor">
      <ATTRIBUTE NAME="size" TYPE="literal" VALUE="small"/>
      <ATTRIBUTE NAME="type" TYPE="literal" VALUE="fan"/>
      <ATTRIBUTE NAME="orientation" TYPE="literal" VALUE="right"/>
      <ATTRIBUTE NAME="colour" TYPE="literal" VALUE="red"/>
    </ENTITY>
    <ENTITY ID="122" IMAGE="fanLeftGreenSmall.gif" TYPE="distractor">
      <ATTRIBUTE NAME="size" TYPE="literal" VALUE="small"/>
      <ATTRIBUTE NAME="type" TYPE="literal" VALUE="fan"/>
      <ATTRIBUTE NAME="orientation" TYPE="literal" VALUE="left"/>
      <ATTRIBUTE NAME="colour" TYPE="literal" VALUE="green"/>
    </ENTITY>
    <ENTITY ID="101" IMAGE="sofaFrontBlueSmall.gif" TYPE="distractor">
      <ATTRIBUTE NAME="size" TYPE="literal" VALUE="small"/>
      <ATTRIBUTE NAME="type" TYPE="literal" VALUE="sofa"/>
      <ATTRIBUTE NAME="orientation" TYPE="literal" VALUE="front"/>
      <ATTRIBUTE NAME="colour" TYPE="literal" VALUE="blue"/>
    </ENTITY>
  </DOMAIN>
  <STRING-DESCRIPTION RE_DURATION="1.32">grosser grauer Stuhl</STRING-DESCRIPTION>
  <ATTRIBUTE-SET>
    <ATTRIBUTE ID="a1" NAME="size" VALUE="large"/>
    <ATTRIBUTE ID="a2" NAME="colour" VALUE="grey"/>
    <ATTRIBUTE ID="a3" NAME="type" VALUE="chair"/>
  </ATTRIBUTE-SET>
</TRIAL>
